setup.py
guess_my_x/__init__.py
guess_my_x/gmx.py
guess_my_x.egg-info/PKG-INFO
guess_my_x.egg-info/SOURCES.txt
guess_my_x.egg-info/dependency_links.txt
guess_my_x.egg-info/not-zip-safe
guess_my_x.egg-info/top_level.txt