Metadata-Version: 1.0
Name: guess-my-x
Version: 0.1
Summary: Guess My X, a Demonstration of Inversion of Control
Home-page: http://github.com/JASchilz/GMX
Author: Joseph Schilz
Author-email: joseph.schilz@gmail.com
License: MIT
Platform: UNKNOWN
